topsis/__init__.py
topsis/file_upload.py
topsis/testcode.py
topsis/topsis.py
topsis/voice_control.py
Topsis_Danish_102203633-0.1.dist-info/METADATA
Topsis_Danish_102203633-0.1.dist-info/WHEEL
Topsis_Danish_102203633-0.1.dist-info/top_level.txt
Topsis_Danish_102203633-0.1.dist-info/RECORD
